<?xml version="1.0" encoding="UTF-8"?>

<mule xmlns:os="http://www.mulesoft.org/schema/mule/os"
    xmlns:apikit="http://www.mulesoft.org/schema/mule/mule-apikit"
	xmlns:salesforce="http://www.mulesoft.org/schema/mule/salesforce" 
    xmlns:anypoint-mq="http://www.mulesoft.org/schema/mule/anypoint-mq"
	xmlns:api-gateway="http://www.mulesoft.org/schema/mule/api-gateway"
	xmlns:tls="http://www.mulesoft.org/schema/mule/tls" xmlns:http="http://www.mulesoft.org/schema/mule/http" xmlns="http://www.mulesoft.org/schema/mule/core" xmlns:doc="http://www.mulesoft.org/schema/mule/documentation" xmlns:xsi="http://www.w3.org/2001/XMLSchema-instance" xsi:schemaLocation="
http://www.mulesoft.org/schema/mule/mule-apikit http://www.mulesoft.org/schema/mule/mule-apikit/current/mule-apikit.xsd http://www.mulesoft.org/schema/mule/core http://www.mulesoft.org/schema/mule/core/current/mule.xsd
http://www.mulesoft.org/schema/mule/http http://www.mulesoft.org/schema/mule/http/current/mule-http.xsd
http://www.mulesoft.org/schema/mule/tls http://www.mulesoft.org/schema/mule/tls/current/mule-tls.xsd
http://www.mulesoft.org/schema/mule/api-gateway http://www.mulesoft.org/schema/mule/api-gateway/current/mule-api-gateway.xsd
http://www.mulesoft.org/schema/mule/anypoint-mq http://www.mulesoft.org/schema/mule/anypoint-mq/current/mule-anypoint-mq.xsd
http://www.mulesoft.org/schema/mule/salesforce http://www.mulesoft.org/schema/mule/salesforce/current/mule-salesforce.xsd
http://www.mulesoft.org/schema/mule/os http://www.mulesoft.org/schema/mule/os/current/mule-os.xsd">
	<apikit:config name="gsusa-troop-api-s-config" raml="gsusa-troop-api-s.raml" outboundHeadersMapName="outboundHeaders" httpStatusVarName="httpStatus" />
		<http:request-config name="SFDC_Token_Request_Config" doc:name="HTTP Request configuration" doc:id="f0e6c1e8-a2df-4fef-9317-277938e60b48" >
		<http:request-connection protocol="HTTPS" host="${auth.sfdc.authTokenrequestURL}" />
	</http:request-config>
	<http:listener-config name="GlobalHttpsConfig" doc:name="HTTP Listener config" doc:id="a22d41f9-0a44-4c78-9b3f-406ace3be498" >
		<http:listener-connection host="0.0.0.0" port="${https.port}" connectionIdleTimeout="${https.global.timeout}" protocol="HTTPS">
			<tls:context >
				<tls:key-store path="${keystore.path}" alias="${keystore.alias}" keyPassword="${keystore.password}" password="${keystore.password}" />
			</tls:context>

		</http:listener-connection>
	</http:listener-config>
	<configuration-properties doc:name="Configuration properties" doc:id="02b7616f-a57a-481a-b664-bfef0ce18536" file="config-${mule.env}.properties" />
	<http:request-config name="SOLR_HTTPS_Configuration" doc:name="HTTP Request configuration" doc:id="6d00ebcf-8b71-41ea-848f-d66ed2fc9720" >
		<http:request-connection protocol="HTTPS" host="${solr.url}" connectionIdleTimeout="${https.solr.timeout}">
			<reconnection >
				<reconnect />
			</reconnection>
			<http:authentication >
				<http:basic-authentication username="${solr.username}" password="${solr.password}" />
			</http:authentication>
		</http:request-connection>
		<http:default-query-params >
			<http:query-param key="commit" value="true" />
		</http:default-query-params>
	</http:request-config>
	<anypoint-mq:default-subscriber-config name="Anypoint_MQ_Default_subscriber" doc:name="Anypoint MQ Default subscriber" doc:id="729c6bb7-6e14-46f5-a938-b816f84ffdeb" >
		<anypoint-mq:connection url="${anypoint.mq.client.url}" clientId="${anypoint.mq.client.app.id}" clientSecret="${anypoint.mq.client.secret}" >
			<reconnection >
				<reconnect count="3" />
			</reconnection>
		</anypoint-mq:connection>
	</anypoint-mq:default-subscriber-config>
	<global-property doc:name="Global Property" doc:id="85c3b5cc-e181-4b56-9a8a-07d1f80e4651" name="mule.env" value="DEV" />
	<salesforce:sfdc-config name="Salesforce_Config" doc:name="Salesforce Config" doc:id="3d103a0b-fbb1-450c-882f-48f7fc621964" >
		<salesforce:cached-basic-connection username="${sfdc.username}" password="${sfdc.password}" securityToken="${sfdc.securityToken}" url="${sfdc.authURL}" />
	</salesforce:sfdc-config>
	
	<http:request-config name="CASE_HTTPS_Request_configuration" doc:name="HTTP Request configuration" doc:id="0a4867d1-7fa5-4b73-9e5f-029d1c902514" >
		<http:request-connection protocol="HTTPS" host="${sfdc.case.create.host}" connectionIdleTimeout="${https.case.timeout}"/>
	</http:request-config>
	<os:object-store name="Auth_Token_Object_store" doc:name="Object store" doc:id="4ef8a5f0-a835-4df3-834f-d0cc78b47833" persistent="false" entryTtl="${os.timeToLive}" entryTtlUnit="HOURS" expirationInterval="${os.expInterval}" />
	<api-gateway:autodiscovery apiId="${autodiscovery.id}" doc:name="API Autodiscovery" doc:id="e2ac5cbf-449d-4d18-8205-3f9e85d8dd58" flowRef="gsusa-troop-api-s-main" />

</mule>
